metafetch.py
metafetch-1.0.3.dist-info/licenses/LICENSE
metafetch-1.0.3.dist-info/METADATA
metafetch-1.0.3.dist-info/WHEEL
metafetch-1.0.3.dist-info/entry_points.txt
metafetch-1.0.3.dist-info/top_level.txt
metafetch-1.0.3.dist-info/RECORD
