Metadata-Version: 2.4
Name: metafetch
Version: 1.0.3
Summary: A beautiful, fast, and comprehensive system information tool
Home-page: https://github.com/volksgeistt/metafetch
Author: Ujjawal Singh / @volksgeistt
Author-email: unrealvolksgeist@gmail.com
License: MIT
Project-URL: Bug Reports, https://github.com/volksgeistt/metafetch/issues
Project-URL: Source, https://github.com/volksgeistt/metafetch
Project-URL: Documentation, https://github.com/volksgeistt/metafetch/blob/main/README.md
Keywords: system information neofetch system-info cli terminal
Classifier: Development Status :: 5 - Production/Stable
Classifier: Environment :: Console
Classifier: Intended Audience :: End Users/Desktop
Classifier: Intended Audience :: System Administrators
Classifier: License :: OSI Approved :: MIT License
Classifier: Operating System :: OS Independent
Classifier: Programming Language :: Python :: 3
Classifier: Programming Language :: Python :: 3.6
Classifier: Programming Language :: Python :: 3.7
Classifier: Programming Language :: Python :: 3.8
Classifier: Programming Language :: Python :: 3.9
Classifier: Programming Language :: Python :: 3.10
Classifier: Programming Language :: Python :: 3.11
Classifier: Topic :: System :: Systems Administration
Classifier: Topic :: Utilities
Requires-Python: >=3.6
License-File: LICENSE
Requires-Dist: psutil>=5.8.0
Dynamic: author
Dynamic: author-email
Dynamic: classifier
Dynamic: description
Dynamic: description-content-type
Dynamic: home-page
Dynamic: keywords
Dynamic: license
Dynamic: license-file
Dynamic: project-url
Dynamic: requires-dist
Dynamic: requires-python
Dynamic: summary
